blockdiag_fences/__init__.py
blockdiag_fences/blockdiag.py
blockdiag_fences-0.0.3.dist-info/LICENSE
blockdiag_fences-0.0.3.dist-info/WHEEL
blockdiag_fences-0.0.3.dist-info/METADATA
blockdiag_fences-0.0.3.dist-info/RECORD
