Metadata-Version: 2.1
Name: blockdiag-fences
Version: 0.0.3
Summary: Inline blockdiag images for Markdown with SuperFences
Home-page: https://github.com/oliversalzburg/markdown-blockdiag.git
License: MIT
Keywords: blockdiag,seqdiag,mkdocs,markdown,superfences
Author: Oliver Salzburg
Author-email: oliver.salzburg@gmail.com
Requires-Python: >=3.8,<4.0
Classifier: Development Status :: 4 - Beta
Classifier: Environment :: Plugins
Classifier: Intended Audience :: Developers
Classifier: License :: OSI Approved :: MIT License
Classifier: Operating System :: OS Independent
Classifier: Programming Language :: Python :: 3
Classifier: Programming Language :: Python :: 3 :: Only
Classifier: Programming Language :: Python :: 3.10
Classifier: Programming Language :: Python :: 3.8
Classifier: Programming Language :: Python :: 3.9
Classifier: Topic :: Documentation
Classifier: Topic :: Software Development :: Documentation
Classifier: Topic :: Text Processing :: Markup :: Markdown
Requires-Dist: actdiag (>=3.0.0,<4.0.0)
Requires-Dist: blockdiag (>=3.0.0,<4.0.0)
Requires-Dist: nwdiag (>=3.0.0,<4.0.0)
Requires-Dist: seqdiag (>=3.0.0,<4.0.0)
Project-URL: Repository, https://github.com/oliversalzburg/markdown-blockdiag.git
